{
    "data":[
        {
            "chainId": 80001,
            "chainType":"",
            "contracts":
            [
                {
                    "contract_name":"ArkreenNotary",
                    "domain_name":"",
                    "version":"",
                    "address":"0x2F87af0Ddb8041bB576AbCCF81F1b4A9E383B7bF",
                    "domain_separator":"",
                    "isProxyed":true,
                    "impl":"0xed65bb735aad436f4f137ee945e83cc58ff5a418",
                    "isERC20":false,
                    "isERC721":false,
                    "symbol":"",
                    "deployer":"0xbaef5d8efa74d3cff297d88c433d7b5d90bf0e49",
                    "owner":"0xbaef5d8efa74d3cff297d88c433d7b5d90bf0e49",
                    "creation_block":34879580,
                    "additional_data":{
                      "DataManager":"0x1ad49e84283e5418175985908459daccd5e60ec8"
                    }
                },
                {
                    "contract_name":"ArkreenReward",
                    "domain_name":"Arkreen Reward",
                    "version":"1",
                    "address":"0x0C571e92D745756712Ded770eF427c6b51Cab6e3",
                    "domain_separator":"",
                    "isProxyed":true,
                    "impl":"0xb2add6df9384eaf6bb7229b6aaee1a16b0222817",
                    "isERC20":false,
                    "isERC721":false,
                    "symbol":"",
                    "deployer":"0xbaef5d8efa74d3cff297d88c433d7b5d90bf0e49",
                    "owner":"0xbaef5d8efa74d3cff297d88c433d7b5d90bf0e49",
                    "creation_block":34886959,
                    "additional_data":{
                      "ValidationAddress":"0x8c4d62477f70c7ea628b52dbf37dcc2e5e4043e2",
                      "ERC20ContractAddress":"0x8ab2299351585097101c91fe4b098d95c18d28a7"
                    }
                },
                {
                    "contract_name":"ArkreenToken",
                    "domain_name":"Arkreen Token",
                    "version":"1",
                    "address":"0x8Ab2299351585097101c91FE4b098d95c18D28a7",
                    "domain_separator":"0x5296a85e034ab40bc8711ed6034f19996f56aed12ae22f7ebbe4c47328b44fc1",
                    "isProxyed":true,
                    "impl":"0x64ffa711abcbc6fabdf0a572889f1ab3025be28e",
                    "isERC20":true,
                    "isERC721":false,
                    "symbol":"tAKRE",
                    "deployer":"0xbaef5d8efa74d3cff297d88c433d7b5d90bf0e49",
                    "owner":"0xbaef5d8efa74d3cff297d88c433d7b5d90bf0e49",
                    "creation_block":34886495,
                    "additional_data":{
                    }
                },
                {
                    "contract_name":"ArkreenMiner",
                    "domain_name":"Arkreen Miner",
                    "version":"1",
                    "address":"0x682e01f8ecc0524085F51CC7dFB54fDB8729ac22",
                    "domain_separator":"0xbd80989d89429d88f7d5215f9cfc0ab85ff072ee6542463adebf7d146b1fe527",
                    "isProxyed":true,
                    "impl":"0xc7a014f4b823788812a9cd08d1c819e882b13b89",
                    "isERC20":false,
                    "isERC721":true,
                    "symbol":"AKREM",
                    "deployer":"0xb53b96e1ef29cb14313c18fa6374ab87df59bcd9",
                    "owner":"0xb53b96e1ef29cb14313c18fa6374ab87df59bcd9",
                    "creation_block":35016696,
                    "additional_data":{
                      "MinerManager":"0xdc641760adAe486Ba9c9878C1f3831c26EbFEAaa",
                      "MinerAuthority":"0xdc641760adAe486Ba9c9878C1f3831c26EbFEAaa",
                      "BaseURI":"https://www.arkreen.com/miners/",
                      "TokenAKRE":"0x8ab2299351585097101c91fe4b098d95c18d28a7",
                      "TokenNative":"0x9c3c9283d3e44854697cd22d3faa240cfb032889"
                    }
                },
                {
                    "contract_name":"ArkreenREC",
                    "domain_name":"Arkreen RE Certificate",
                    "version":"1",
                    "address":"0x32Dbe18BBc2C752203b6e1bE87EdE5655A091dFa",
                    "domain_separator":"",
                    "isProxyed":true,
                    "impl":"0x51016eafbc75058391beeea156ab6b8ad9b92e52",
                    "isERC20":false,
                    "isERC721":true,
                    "symbol":"AREC",
                    "deployer":"0xb53b96e1ef29cb14313c18fa6374ab87df59bcd9",
                    "owner":"0xb53b96e1ef29cb14313c18fa6374ab87df59bcd9",
                    "creation_block":	35382072,
                    "additional_data":{
                      "TokenAKRE":"0x8ab2299351585097101c91fe4b098d95c18d28a7",
                      "BaseURI":"https://www.arkreen.com/AREC/",
                      "ArkreenRegistry":"0xfecbd33525d9b869e5f3cab895cd6d7a666209ee"
                    }
                }
            ]
        },
        {
            "chainId": 137,
            "contracts":
            [
              {
                "contract_name":"ArkreenNotary",
                "domain_name":"",
                "version":"",
                "address":"0xb006A62f7e0f3715126AA76A968Ac709d0Fc0341",
                "domain_separator":"",
                "isProxyed":true,
                "impl":"0x2d2249a2edeedbe7e8b74c2e91221d7d3e6cbe52",
                "isERC20":false,
                "isERC721":false,
                "symbol":"",
                "deployer":"0xbaef5d8efa74d3cff297d88c433d7b5d90bf0e49",
                "owner":"0xbaef5d8efa74d3cff297d88c433d7b5d90bf0e49",
                "creation_block":42434577,
                "additional_data":{
                  "DataManager":"0x8a13a3614c2c0b91f4c4506fb80bb85db711db0b"
                }
              },
              {
                "contract_name":"ArkreenMiner",
                "domain_name":"Arkreen Miner",
                "version":"1",
                "address":"0xbf8eF5D950F78eF8edBB8674a48cDACa675831Ae",
                "domain_separator":"0x2dd1ec801dc75b1bcd6d26f334939c9b176fc59ad9e6dd01ff4a88db64c08c6e",
                "isProxyed":true,
                "impl":"0x7a0df5effdbb91df24cb7f7db2500ce9721a7a78",
                "isERC20":false,
                "isERC721":true,
                "symbol":"AKREM",
                "deployer":"0x05d1e64fc523105ceced7c5ca70993cd69b8e808",
                "owner":"0x05d1e64fc523105ceced7c5ca70993cd69b8e808",
                "creation_block":42522028,
                "additional_data":{
                  "MinerManager":"0x78993487B21b8Cb8F0442F3FFCB0FC880Da34905",
                  "MinerAuthority":"0x78993487B21b8Cb8F0442F3FFCB0FC880Da34905",
                  "BaseURI":"https://www.arkreen.com/miners/",
                  "TokenAKRE":"0x21b101f5d61a66037634f7e1beb5a733d9987d57",
                  "TokenNative":"0x0d500b1d8e8ef31e21c99d1db9a6444d3adf1270"
                }
              },
              {
                "contract_name":"ArkreenREC",
                "domain_name":"Arkreen RE Certificate",
                "version":"1",
                "address":"0x954585adF9425F66a0a2FD8e10682EB7c4F1f1fD",
                "domain_separator":"",
                "isProxyed":true,
                "impl":" 0x966721720dc732464d2c5594aff9b0aa52e1b0e8",
                "isERC20":false,
                "isERC721":true,
                "symbol":"AREC",
                "deployer":"0x05d1e64fc523105ceced7c5ca70993cd69b8e808",
                "owner":"0x05d1e64fc523105ceced7c5ca70993cd69b8e808",
                "creation_block":	40626128,
                "additional_data":{
                  "TokenAKRE":"0x21b101f5d61a66037634f7e1beb5a733d9987d57",
                  "BaseURI":"https://www.arkreen.com/AREC/",
                  "ArkreenRegistry":"0xb17facaca106fb3d216923db6cabfc7c0517029d"
                }
              },
              {
                "contract_name":"ArkreenReward",
                "domain_name":"Arkreen Reward",
                "version":"1",
                "address":"0x44082E783bA0aBB62975e77E48aF355B2bF3d440",
                "domain_separator":"",
                "isProxyed":true,
                "impl":"0x2f47c3346300ca8c04e0af15c527216f5363910c",
                "isERC20":false,
                "isERC721":false,
                "symbol":"",
                "deployer":"0x05d1e64fc523105ceced7c5ca70993cd69b8e808",
                "owner":"0x05d1e64fc523105ceced7c5ca70993cd69b8e808",
                "creation_block":42757121,
                "additional_data":{
                  "ValidationAddress":"0x741e2403b63a41188e72dc3897d730a746d9181e",
                  "ERC20ContractAddress":"0x21b101f5d61a66037634f7e1beb5a733d9987d57"
                }
              },
              {
                "contract_name":"ArkreenToken",
                "domain_name":"Arkreen Token",
                "version":"1",
                "address":"0x21B101f5d61A66037634f7e1BeB5a733d9987D57",
                "domain_separator":"0xf56e1196f2471fd2d6179ed14349a143a366f9a9b34d7938e161675ad08d937b",
                "isProxyed":true,
                "impl":"0xe47ee63316855522f4719c36d75964f9b8453a94",
                "isERC20":true,
                "isERC721":false,
                "symbol":"tAKRE",
                "deployer":"0x05d1e64fc523105ceced7c5ca70993cd69b8e808",
                "owner":"0x05d1e64fc523105ceced7c5ca70993cd69b8e808",
                "creation_block":41127489,
                "additional_data":{
                }
              }
            ]
        }
    ],

    "infura_provider":[
      "0ab4ce267db54906802cb43b24e5b0f7",
      "295cce92179b4be498665b1b16dfee34",
      "68a2de3671204e8c91871ee8d0c927f3"
    ]
}